cegalprizm/scripting_server/__init__.py
cegalprizm/scripting_server/__main__.py
cegalprizm/scripting_server/script_library.py
cegalprizm/scripting_server/script_parameters.py
cegalprizm/scripting_server/scripting_server_pb2.py
cegalprizm/scripting_server/task_registry.py
cegalprizm/scripting_server/tasks/create_function.py
cegalprizm/scripting_server/tasks/execute_function.py
cegalprizm/scripting_server/tasks/run_script.py
cegalprizm_scripting_server-1.0.1.dist-info/LICENSE
cegalprizm_scripting_server-1.0.1.dist-info/METADATA
cegalprizm_scripting_server-1.0.1.dist-info/WHEEL
cegalprizm_scripting_server-1.0.1.dist-info/top_level.txt
cegalprizm_scripting_server-1.0.1.dist-info/RECORD
